wagalytics/__init__.py
wagalytics/urls.py
wagalytics/views.py
wagalytics/wagtail_hooks.py
wagalytics/static/wagalytics/.gitkeep
wagalytics/static/wagalytics/bundle.js.map
wagalytics/static/wagalytics/vendors.bundle.js
wagalytics/static/wagalytics/wagalytics.bundle.js
wagalytics/templates/wagalytics/dashboard.html
wagalytics_tier-1.0rc1.dist-info/LICENSE
wagalytics_tier-1.0rc1.dist-info/METADATA
wagalytics_tier-1.0rc1.dist-info/WHEEL
wagalytics_tier-1.0rc1.dist-info/top_level.txt
wagalytics_tier-1.0rc1.dist-info/RECORD
